example_himal/__about__.py
example_himal/__init__.py
example_himal/__main__.py
example_himal/cli/__init__.py
example_himal-0.1.0.dist-info/METADATA
example_himal-0.1.0.dist-info/WHEEL
example_himal-0.1.0.dist-info/entry_points.txt
example_himal-0.1.0.dist-info/licenses/LICENSE.txt
example_himal-0.1.0.dist-info/RECORD
